{
  "RunType": "HTTP",
  "Labels": "svc-b.mesh-exp , client",
  "StartTime": "2026-03-19T06:20:26.529876349Z",
  "RequestedQPS": "4000",
  "RequestedDuration": "2m0s",
  "ActualQPS": 1625.1222221878213,
  "ActualDuration": 120045740152,
  "NumThreads": 200,
  "Version": "1.75.0",
  "DurationHistogram": {
    "Count": 195089,
    "Min": 0.000330925,
    "Max": 1.172599099,
    "Sum": 23999.625281356995,
    "Avg": 0.12301885437598735,
    "StdDev": 0.09088651687684243,
    "Data": [
      {
        "Start": 0.000330925,
        "End": 0.001,
        "Percent": 0.6740513304184245,
        "Count": 1315
      },
      {
        "Start": 0.001,
        "End": 0.002,
        "Percent": 2.8935511484501943,
        "Count": 4330
      },
      {
        "Start": 0.002,
        "End": 0.003,
        "Percent": 4.841380088062372,
        "Count": 3800
      },
      {
        "Start": 0.003,
        "End": 0.004,
        "Percent": 6.243304338020083,
        "Count": 2735
      },
      {
        "Start": 0.004,
        "End": 0.005,
        "Percent": 7.2259327793981205,
        "Count": 1917
      },
      {
        "Start": 0.005,
        "End": 0.006,
        "Percent": 7.9527805258112965,
        "Count": 1418
      },
      {
        "Start": 0.006,
        "End": 0.007,
        "Percent": 8.559683016469407,
        "Count": 1184
      },
      {
        "Start": 0.007,
        "End": 0.008,
        "Percent": 9.114814264258877,
        "Count": 1083
      },
      {
        "Start": 0.008,
        "End": 0.009000000000000001,
        "Percent": 9.568453372563292,
        "Count": 885
      },
      {
        "Start": 0.009000000000000001,
        "End": 0.01,
        "Percent": 9.980060382697127,
        "Count": 803
      },
      {
        "Start": 0.01,
        "End": 0.011,
        "Percent": 10.346047188718995,
        "Count": 714
      },
      {
        "Start": 0.011,
        "End": 0.012,
        "Percent": 10.66180051156139,
        "Count": 616
      },
      {
        "Start": 0.012,
        "End": 0.014,
        "Percent": 11.239998154688372,
        "Count": 1128
      },
      {
        "Start": 0.014,
        "End": 0.016,
        "Percent": 11.752072131181153,
        "Count": 999
      },
      {
        "Start": 0.016,
        "End": 0.018000000000000002,
        "Percent": 12.219038490125019,
        "Count": 911
      },
      {
        "Start": 0.018000000000000002,
        "End": 0.02,
        "Percent": 12.660375520916094,
        "Count": 861
      },
      {
        "Start": 0.02,
        "End": 0.025,
        "Percent": 13.68503606046471,
        "Count": 1999
      },
      {
        "Start": 0.025,
        "End": 0.03,
        "Percent": 14.573861160803531,
        "Count": 1734
      },
      {
        "Start": 0.03,
        "End": 0.035,
        "Percent": 15.469349886462076,
        "Count": 1747
      },
      {
        "Start": 0.035,
        "End": 0.04,
        "Percent": 16.415072095300093,
        "Count": 1845
      },
      {
        "Start": 0.04,
        "End": 0.045,
        "Percent": 17.472025588321227,
        "Count": 2062
      },
      {
        "Start": 0.045,
        "End": 0.05,
        "Percent": 18.69556971433551,
        "Count": 2387
      },
      {
        "Start": 0.05,
        "End": 0.06,
        "Percent": 21.475839232350364,
        "Count": 5424
      },
      {
        "Start": 0.06,
        "End": 0.07,
        "Percent": 24.990132708661175,
        "Count": 6856
      },
      {
        "Start": 0.07,
        "End": 0.08,
        "Percent": 29.90993854087109,
        "Count": 9598
      },
      {
        "Start": 0.08,
        "End": 0.09,
        "Percent": 36.41466202604965,
        "Count": 12690
      },
      {
        "Start": 0.09,
        "End": 0.1,
        "Percent": 43.26845696066923,
        "Count": 13371
      },
      {
        "Start": 0.1,
        "End": 0.12,
        "Percent": 56.15180763651462,
        "Count": 25134
      },
      {
        "Start": 0.12,
        "End": 0.14,
        "Percent": 67.29902762328989,
        "Count": 21747
      },
      {
        "Start": 0.14,
        "End": 0.16,
        "Percent": 75.32254509480289,
        "Count": 15653
      },
      {
        "Start": 0.16,
        "End": 0.18,
        "Percent": 81.07940478448297,
        "Count": 11231
      },
      {
        "Start": 0.18,
        "End": 0.2,
        "Percent": 85.20675179020857,
        "Count": 8052
      },
      {
        "Start": 0.2,
        "End": 0.25,
        "Percent": 91.83449605052053,
        "Count": 12930
      },
      {
        "Start": 0.25,
        "End": 0.3,
        "Percent": 95.53024517015311,
        "Count": 7210
      },
      {
        "Start": 0.3,
        "End": 0.35000000000000003,
        "Percent": 97.49293912009391,
        "Count": 3829
      },
      {
        "Start": 0.35000000000000003,
        "End": 0.4,
        "Percent": 98.50837310150752,
        "Count": 1981
      },
      {
        "Start": 0.4,
        "End": 0.45,
        "Percent": 99.14551819938592,
        "Count": 1243
      },
      {
        "Start": 0.45,
        "End": 0.5,
        "Percent": 99.47613653255694,
        "Count": 645
      },
      {
        "Start": 0.5,
        "End": 0.6,
        "Percent": 99.78573881664266,
        "Count": 604
      },
      {
        "Start": 0.6,
        "End": 0.7000000000000001,
        "Percent": 99.92516236179385,
        "Count": 272
      },
      {
        "Start": 0.7000000000000001,
        "End": 0.8,
        "Percent": 99.97539584497332,
        "Count": 98
      },
      {
        "Start": 0.8,
        "End": 0.9,
        "Percent": 99.99436154780639,
        "Count": 37
      },
      {
        "Start": 0.9,
        "End": 1,
        "Percent": 99.99794965374778,
        "Count": 7
      },
      {
        "Start": 1,
        "End": 1.172599099,
        "Percent": 100,
        "Count": 4
      }
    ],
    "Percentiles": [
      {
        "Percentile": 50,
        "Value": 0.11044998806397709
      },
      {
        "Percentile": 75,
        "Value": 0.15919600076662618
      },
      {
        "Percentile": 90,
        "Value": 0.23616047950502708
      },
      {
        "Percentile": 99,
        "Value": 0.4385804505229286
      },
      {
        "Percentile": 99.9,
        "Value": 0.6819525735294132
      }
    ]
  },
  "ErrorsDurationHistogram": {
    "Count": 0,
    "Min": 0,
    "Max": 0,
    "Sum": 0,
    "Avg": 0,
    "StdDev": 0,
    "Data": null
  },
  "Exactly": 0,
  "Jitter": false,
  "Uniform": false,
  "NoCatchUp": false,
  "RunID": 0,
  "AccessLoggerInfo": "",
  "ID": "2026-03-19-062025_svc_b_mesh_exp_client",
  "RetCodes": {
    "200": 195089
  },
  "IPCountMap": {
    "10.111.251.152:80": 200
  },
  "Insecure": false,
  "MTLS": false,
  "CACert": "",
  "Cert": "",
  "Key": "",
  "UnixDomainSocket": "",
  "URL": "http://svc-b.mesh-exp",
  "NumConnections": 1,
  "Compression": false,
  "DisableFastClient": false,
  "HTTP10": false,
  "H2": false,
  "DisableKeepAlive": false,
  "AllowHalfClose": false,
  "FollowRedirects": false,
  "Resolve": "",
  "HTTPReqTimeOut": 3000000000,
  "UserCredentials": "",
  "ContentType": "",
  "Payload": "",
  "MethodOverride": "",
  "LogErrors": true,
  "SequentialWarmup": false,
  "ConnReuseRange": [
    0,
    0
  ],
  "NoResolveEachConn": false,
  "Offset": 0,
  "Resolution": 0.001,
  "Sizes": {
    "Count": 195089,
    "Min": 167,
    "Max": 167,
    "Sum": 32579863,
    "Avg": 167,
    "StdDev": 0,
    "Data": [
      {
        "Start": 167,
        "End": 167,
        "Percent": 100,
        "Count": 195089
      }
    ]
  },
  "HeaderSizes": {
    "Count": 195089,
    "Min": 161,
    "Max": 161,
    "Sum": 31409329,
    "Avg": 161,
    "StdDev": 0,
    "Data": [
      {
        "Start": 161,
        "End": 161,
        "Percent": 100,
        "Count": 195089
      }
    ]
  },
  "Sockets": [
    1,
    1,
    1,
    1,
    1,
    1,
    1,
    1,
    1,
    1,
    1,
    1,
    1,
    1,
    1,
    1,
    1,
    1,
    1,
    1,
    1,
    1,
    1,
    1,
    1,
    1,
    1,
    1,
    1,
    1,
    1,
    1,
    1,
    1,
    1,
    1,
    1,
    1,
    1,
    1,
    1,
    1,
    1,
    1,
    1,
    1,
    1,
    1,
    1,
    1,
    1,
    1,
    1,
    1,
    1,
    1,
    1,
    1,
    1,
    1,
    1,
    1,
    1,
    1,
    1,
    1,
    1,
    1,
    1,
    1,
    1,
    1,
    1,
    1,
    1,
    1,
    1,
    1,
    1,
    1,
    1,
    1,
    1,
    1,
    1,
    1,
    1,
    1,
    1,
    1,
    1,
    1,
    1,
    1,
    1,
    1,
    1,
    1,
    1,
    1,
    1,
    1,
    1,
    1,
    1,
    1,
    1,
    1,
    1,
    1,
    1,
    1,
    1,
    1,
    1,
    1,
    1,
    1,
    1,
    1,
    1,
    1,
    1,
    1,
    1,
    1,
    1,
    1,
    1,
    1,
    1,
    1,
    1,
    1,
    1,
    1,
    1,
    1,
    1,
    1,
    1,
    1,
    1,
    1,
    1,
    1,
    1,
    1,
    1,
    1,
    1,
    1,
    1,
    1,
    1,
    1,
    1,
    1,
    1,
    1,
    1,
    1,
    1,
    1,
    1,
    1,
    1,
    1,
    1,
    1,
    1,
    1,
    1,
    1,
    1,
    1,
    1,
    1,
    1,
    1,
    1,
    1,
    1,
    1,
    1,
    1,
    1,
    1,
    1,
    1,
    1,
    1,
    1,
    1,
    1,
    1,
    1,
    1,
    1,
    1
  ],
  "SocketCount": 200,
  "ConnectionStats": {
    "Count": 200,
    "Min": 0.000479558,
    "Max": 0.067148289,
    "Sum": 3.766365976000001,
    "Avg": 0.018831829880000005,
    "StdDev": 0.019666539040036877,
    "Data": [
      {
        "Start": 0.000479558,
        "End": 0.001,
        "Percent": 1.5,
        "Count": 3
      },
      {
        "Start": 0.001,
        "End": 0.002,
        "Percent": 7,
        "Count": 11
      },
      {
        "Start": 0.002,
        "End": 0.003,
        "Percent": 13,
        "Count": 12
      },
      {
        "Start": 0.003,
        "End": 0.004,
        "Percent": 18.5,
        "Count": 11
      },
      {
        "Start": 0.004,
        "End": 0.005,
        "Percent": 25.5,
        "Count": 14
      },
      {
        "Start": 0.005,
        "End": 0.006,
        "Percent": 33,
        "Count": 15
      },
      {
        "Start": 0.006,
        "End": 0.007,
        "Percent": 39,
        "Count": 12
      },
      {
        "Start": 0.007,
        "End": 0.008,
        "Percent": 48,
        "Count": 18
      },
      {
        "Start": 0.008,
        "End": 0.009000000000000001,
        "Percent": 51,
        "Count": 6
      },
      {
        "Start": 0.009000000000000001,
        "End": 0.01,
        "Percent": 55.5,
        "Count": 9
      },
      {
        "Start": 0.01,
        "End": 0.011,
        "Percent": 59.5,
        "Count": 8
      },
      {
        "Start": 0.011,
        "End": 0.012,
        "Percent": 63.5,
        "Count": 8
      },
      {
        "Start": 0.012,
        "End": 0.014,
        "Percent": 64.5,
        "Count": 2
      },
      {
        "Start": 0.014,
        "End": 0.016,
        "Percent": 65,
        "Count": 1
      },
      {
        "Start": 0.018000000000000002,
        "End": 0.02,
        "Percent": 65.5,
        "Count": 1
      },
      {
        "Start": 0.02,
        "End": 0.025,
        "Percent": 69.5,
        "Count": 8
      },
      {
        "Start": 0.025,
        "End": 0.03,
        "Percent": 76,
        "Count": 13
      },
      {
        "Start": 0.03,
        "End": 0.035,
        "Percent": 80.5,
        "Count": 9
      },
      {
        "Start": 0.04,
        "End": 0.045,
        "Percent": 84,
        "Count": 7
      },
      {
        "Start": 0.045,
        "End": 0.05,
        "Percent": 88,
        "Count": 8
      },
      {
        "Start": 0.05,
        "End": 0.06,
        "Percent": 92.5,
        "Count": 9
      },
      {
        "Start": 0.06,
        "End": 0.067148289,
        "Percent": 100,
        "Count": 15
      }
    ],
    "Percentiles": [
      {
        "Percentile": 50,
        "Value": 0.008666666666666668
      },
      {
        "Percentile": 75,
        "Value": 0.02923076923076923
      },
      {
        "Percentile": 90,
        "Value": 0.05444444444444445
      },
      {
        "Percentile": 99,
        "Value": 0.0661951838
      },
      {
        "Percentile": 99.9,
        "Value": 0.06705297848000001
      }
    ]
  },
  "AbortOn": 0
}
